trivium_python_sdk/__init__.py
trivium_python_sdk/api_client.py
trivium_python_sdk/api_response.py
trivium_python_sdk/configuration.py
trivium_python_sdk/exceptions.py
trivium_python_sdk/py.typed
trivium_python_sdk/rest.py
trivium_python_sdk/security.py
trivium_python_sdk/api/__init__.py
trivium_python_sdk/api/cash_api.py
trivium_python_sdk/api/fixed_deposit_api.py
trivium_python_sdk/api/managed_portfolios_api.py
trivium_python_sdk/api/payments_api.py
trivium_python_sdk/api/statement_api.py
trivium_python_sdk/api/trading_api.py
trivium_python_sdk/api/transactions_api.py
trivium_python_sdk/api/user_api.py
trivium_python_sdk/models/__init__.py
trivium_python_sdk/models/account.py
trivium_python_sdk/models/account_status.py
trivium_python_sdk/models/account_type.py
trivium_python_sdk/models/action.py
trivium_python_sdk/models/ad_hoc_payout_intention.py
trivium_python_sdk/models/approve_payout.py
trivium_python_sdk/models/approve_payout_deprecated.py
trivium_python_sdk/models/asset_class.py
trivium_python_sdk/models/asset_class_proportion.py
trivium_python_sdk/models/bad_gateway.py
trivium_python_sdk/models/bad_request.py
trivium_python_sdk/models/balance.py
trivium_python_sdk/models/balances.py
trivium_python_sdk/models/bank_account_details.py
trivium_python_sdk/models/beneficiary_details.py
trivium_python_sdk/models/buy_sell.py
trivium_python_sdk/models/cash_account_activated.py
trivium_python_sdk/models/cash_callback_event.py
trivium_python_sdk/models/cash_deposit.py
trivium_python_sdk/models/cash_inbound_callback_event.py
trivium_python_sdk/models/cash_redemption.py
trivium_python_sdk/models/charge_type.py
trivium_python_sdk/models/company_details.py
trivium_python_sdk/models/composition.py
trivium_python_sdk/models/corporate_beneficiary_details.py
trivium_python_sdk/models/country_proportion.py
trivium_python_sdk/models/create_account_request.py
trivium_python_sdk/models/create_onboarding_document_request.py
trivium_python_sdk-0.2.10.dist-info/licenses/LICENSE
trivium_python_sdk-0.2.10.dist-info/METADATA
trivium_python_sdk-0.2.10.dist-info/WHEEL
trivium_python_sdk-0.2.10.dist-info/top_level.txt
trivium_python_sdk-0.2.10.dist-info/RECORD
