Metadata-Version: 2.4
Name: trivium-python-sdk
Version: 0.2.10
Summary: trivium-python-sdk
Home-page: https://github.com/trivium-capital/trivium-python-sdk
Author: William Haw
Author-email: william@triviumcapital.tech
Keywords: OpenAPI,OpenAPI-Generator,trivium-python-sdk
License-File: LICENSE
Requires-Dist: urllib3<3.0.0,>=1.25.3
Requires-Dist: python-dateutil>=2.8.2
Requires-Dist: pydantic>=2
Requires-Dist: typing-extensions>=4.7.1
Requires-Dist: cryptography>=41
Dynamic: author
Dynamic: author-email
Dynamic: description
Dynamic: description-content-type
Dynamic: home-page
Dynamic: keywords
Dynamic: license-file
Dynamic: requires-dist
Dynamic: summary
